pybigdata/__init__.py
pybigdata/file_reader.py
pybigdata/linear_algebra.py
pybigdata/optimization.py
pybigdata/probabilities.py
pybigdata/searching.py
pybigdata/sorting.py
pybigdata-0.0.2.dist-info/AUTHORS.md
pybigdata-0.0.2.dist-info/LICENSE
pybigdata-0.0.2.dist-info/METADATA
pybigdata-0.0.2.dist-info/WHEEL
pybigdata-0.0.2.dist-info/top_level.txt
pybigdata-0.0.2.dist-info/RECORD
