Metadata-Version: 2.1
Name: pybigdata
Version: 0.0.2
Summary: This python library will eat bigdata.
Home-page: https://github.com/AlirezaSheikhiy/pybigdata
Author: Alireza Sheikhiy
Author-email: alir3zash3ikhiy@gmail.com
License-File: LICENSE
License-File: AUTHORS.md
